MANIFEST.in
setup.cfg
setup.py
camtono/parser/__init__.py
camtono/parser/clean.py
camtono/parser/dialects.py
camtono/parser/format.py
camtono/parser/keywords.py
camtono/parser/parse.py
camtono/parser/standard.py
camtono_parser.egg-info/PKG-INFO
camtono_parser.egg-info/SOURCES.txt
camtono_parser.egg-info/dependency_links.txt
camtono_parser.egg-info/requires.txt
camtono_parser.egg-info/top_level.txt