Metadata-Version: 2.1
Name: camtono-parser
Version: 0.0.33
Summary: SQL parser and formatter
Home-page: https://bitbucket.org/adarainc/camtono-parser-pkg
Author: DOT
Author-email: dot@adara.com
License: UNKNOWN
Platform: UNKNOWN
Classifier: Programming Language :: Python :: 3
Classifier: License :: OSI Approved :: MIT License
Classifier: Operating System :: OS Independent
Requires-Python: >=3.6
